sb_stealth_wrapper/__init__.py
sb_stealth_wrapper/driver.py
sb_stealth_wrapper/py.typed
sb_stealth_wrapper/strategies/__init__.py
sb_stealth_wrapper/strategies/base.py
sb_stealth_wrapper/strategies/evasion.py
sb_stealth_wrapper/strategies/input.py
sb_stealth_wrapper-0.4.0.dist-info/licenses/LICENSE
sb_stealth_wrapper-0.4.0.dist-info/METADATA
sb_stealth_wrapper-0.4.0.dist-info/WHEEL
sb_stealth_wrapper-0.4.0.dist-info/top_level.txt
sb_stealth_wrapper-0.4.0.dist-info/RECORD
