Metadata-Version: 2.4
Name: sb-stealth-wrapper
Version: 0.4.0
Summary: A robust, plug-and-play wrapper around SeleniumBase UC Mode for stealth web automation.
Author-email: Dhiraj Das <dhirajdas.666@gmail.com>
License: MIT
Project-URL: Homepage, https://www.dhirajdas.dev
Project-URL: Repository, https://github.com/godhiraj-code/stealthautomation
Project-URL: Documentation, https://github.com/godhiraj-code/stealthautomation#readme
Project-URL: Bug Tracker, https://github.com/godhiraj-code/stealthautomation/issues
Keywords: selenium,stealth,automation,bot-detection,cloudflare,turnstile,web-scraping,testing
Classifier: Development Status :: 4 - Beta
Classifier: Intended Audience :: Developers
Classifier: License :: OSI Approved :: MIT License
Classifier: Operating System :: OS Independent
Classifier: Programming Language :: Python :: 3
Classifier: Programming Language :: Python :: 3.8
Classifier: Programming Language :: Python :: 3.9
Classifier: Programming Language :: Python :: 3.10
Classifier: Programming Language :: Python :: 3.11
Classifier: Programming Language :: Python :: 3.12
Classifier: Topic :: Software Development :: Testing
Classifier: Topic :: Internet :: WWW/HTTP :: Browsers
Requires-Python: >=3.8
License-File: LICENSE
Requires-Dist: seleniumbase>=4.20.0
Provides-Extra: dev
Requires-Dist: pytest>=7.0.0; extra == "dev"
Requires-Dist: black>=23.0.0; extra == "dev"
Requires-Dist: isort>=5.12.0; extra == "dev"
Requires-Dist: mypy>=1.0.0; extra == "dev"
Dynamic: license-file
